{
    "type": "object",
    "properties": {
      "source": {
        "type": "string",
        "required": true,
        "title": "File name and path"
      },
      "data": {
        "type": "string",
        "required": true,
        "title": "File to upload"
      },
      "access": {
        "type": "string",
        "required": false,
        "title": "Access (private or public)"
      },
      "uploadType": {
        "type": "string",
        "required": false,
        "title": "Uplaod type (direct or resumable)"
      },
      "fileToUpdate": {
        "type": "string",
        "required": true,
        "title": "Provide Id of the file you want to look up"
    }
    }
  }
  